{
  "id": "0712",
  "slug": "minimum-ascii-delete-sum-for-two-strings",
  "title": "Minimum ASCII Delete Sum for Two Strings",
  "difficulty": "Medium",
  "topics": [
    "String",
    "Dynamic Programming"
  ],
  "description": "Given two strings s1 and s2, return the lowest ASCII sum of deleted characters to make two strings equal.\nExample 1:\nExample 2:\nConstraints:",
  "constraints": [
    "1 <= s1.length, s2.length <= 1000",
    "s1 and s2 consist of lowercase English letters."
  ],
  "examples": [
    {
      "example_text": "Input: s1 = \"sea\", s2 = \"eat\"\nOutput: 231\nExplanation: Deleting \"s\" from \"sea\" adds the ASCII value of \"s\" (115) to the sum.\nDeleting \"t\" from \"eat\" adds 116 to the sum.\nAt the end, both strings are equal, and 115 + 116 = 231 is the minimum sum possible to achieve this."
    },
    {
      "example_text": "Input: s1 = \"delete\", s2 = \"leet\"\nOutput: 403\nExplanation: Deleting \"dee\" from \"delete\" to turn the string into \"let\",\nadds 100[d] + 101[e] + 101[e] to the sum.\nDeleting \"e\" from \"leet\" adds 101[e] to the sum.\nAt the end, both strings are equal to \"let\", and the answer is 100+101+101+101 = 403.\nIf instead we turned both strings into \"lee\" or \"eet\", we would get answers of 433 or 417, which are higher."
    }
  ],
  "hints": [
    "Let dp(i, j) be the answer for inputs s1[i:] and s2[j:]."
  ],
  "starter_code": "class Solution:\n    def minimumDeleteSum(self, s1: str, s2: str) -> int:\n        ",
  "test_cases": []
}