{
  "id": "0878",
  "slug": "nth-magical-number",
  "title": "Nth Magical Number",
  "difficulty": "Hard",
  "topics": [
    "Math",
    "Binary Search"
  ],
  "description": "A positive integer is magical if it is divisible by either a or b.\nGiven the three integers n, a, and b, return the nth magical number. Since the answer may be very large, return it modulo 109 + 7.\nExample 1:\nExample 2:\nConstraints:",
  "constraints": [
    "1 <= n <= 109",
    "2 <= a, b <= 4 * 104"
  ],
  "examples": [
    {
      "example_text": "Input: n = 1, a = 2, b = 3\nOutput: 2"
    },
    {
      "example_text": "Input: n = 4, a = 2, b = 3\nOutput: 6"
    }
  ],
  "hints": [],
  "starter_code": "class Solution:\n    def nthMagicalNumber(self, n: int, a: int, b: int) -> int:\n        ",
  "test_cases": []
}