{
  "id": "1312",
  "slug": "minimum-insertion-steps-to-make-a-string-palindrome",
  "title": "Minimum Insertion Steps to Make a String Palindrome",
  "difficulty": "Hard",
  "topics": [
    "String",
    "Dynamic Programming"
  ],
  "description": "Given a string s. In one step you can insert any character at any index of the string.\nReturn the minimum number of steps to make s palindrome.\nA Palindrome String is one that reads the same backward as well as forward.\nExample 1:\nExample 2:\nExample 3:\nConstraints:",
  "constraints": [
    "1 <= s.length <= 500",
    "s consists of lowercase English letters."
  ],
  "examples": [
    {
      "example_text": "Input: s = \"zzazz\"\nOutput: 0\nExplanation: The string \"zzazz\" is already palindrome we do not need any insertions."
    },
    {
      "example_text": "Input: s = \"mbadm\"\nOutput: 2\nExplanation: String can be \"mbdadbm\" or \"mdbabdm\"."
    },
    {
      "example_text": "Input: s = \"leetcode\"\nOutput: 5\nExplanation: Inserting 5 characters the string becomes \"leetcodocteel\"."
    }
  ],
  "hints": [
    "Is dynamic programming suitable for this problem ?",
    "If we know the longest palindromic sub-sequence is x and the length of the string is n then, what is the answer to this problem? It is n - x as we need n - x insertions to make the remaining characters also palindrome."
  ],
  "starter_code": "class Solution:\n    def minInsertions(self, s: str) -> int:\n        ",
  "test_cases": []
}